csfloat_inspector/__init__.py
csfloat_inspector-1.1.0.dist-info/METADATA
csfloat_inspector-1.1.0.dist-info/WHEEL
csfloat_inspector-1.1.0.dist-info/entry_points.txt
csfloat_inspector-1.1.0.dist-info/licenses/LICENSE
csfloat_inspector-1.1.0.dist-info/RECORD
