Metadata-Version: 2.4
Name: csfloat-inspector
Version: 1.1.0
Summary: An inspector of CSFloat
Project-URL: Homepage, https://github.com/GamerNoTitle/csfloat-inspector
Project-URL: Issues, https://github.com/GamerNoTitle/csfloat-inspector/issues
Project-URL: Source, https://github.com/GamerNoTitle/csfloat-inspector
Author-email: GamerNoTitle <GamerNoTitle@outlook.com>
License: AGPL-3.0-or-later
License-File: LICENSE
Classifier: Operating System :: OS Independent
Classifier: Programming Language :: Python :: 3
Requires-Python: >=3.11
Requires-Dist: httpx>=0.28.1
